orchestrate/__init__.py
orchestrate/_internal/__init__.py
orchestrate/_internal/api.py
orchestrate/_internal/batch.py
orchestrate/_internal/convert.py
orchestrate/_internal/exceptions.py
orchestrate/_internal/fhir.py
orchestrate/_internal/http_handler.py
orchestrate/_internal/identity/advisories.py
orchestrate/_internal/identity/api.py
orchestrate/_internal/identity/demographic.py
orchestrate/_internal/identity/local_hashing.py
orchestrate/_internal/identity/monitoring.py
orchestrate/_internal/insight.py
orchestrate/_internal/terminology.py
orchestrate/_internal/version.py
orchestrate/convert.py
orchestrate/exceptions.py
orchestrate/fhir.py
orchestrate/identity/__init__.py
orchestrate/identity/monitoring.py
orchestrate/insight.py
orchestrate/terminology.py
orchestrate_api-3.3.0.dist-info/METADATA
orchestrate_api-3.3.0.dist-info/WHEEL
orchestrate_api-3.3.0.dist-info/RECORD
