Metadata-Version: 2.4
Name: orchestrate-api
Version: 3.3.0
Summary: SDK for the Orchestrate API at api.careevolutionapi.com
License: Apache-2.0
Keywords: careevolution,rosetta,orchestrate
Author: Jeremy Fortune
Author-email: jeremy@careevolution.com
Requires-Python: >=3.9,<4.0
Classifier: License :: OSI Approved :: Apache Software License
Classifier: Programming Language :: Python :: 3
Classifier: Programming Language :: Python :: 3.9
Classifier: Programming Language :: Python :: 3.10
Classifier: Programming Language :: Python :: 3.11
Classifier: Programming Language :: Python :: 3.12
Classifier: Programming Language :: Python :: 3.13
Classifier: Programming Language :: Python :: 3.14
Classifier: Topic :: Software Development :: Libraries :: Python Modules
Requires-Dist: requests (>=2.31.0,<3.0.0)
Requires-Dist: typing-extensions (>=4.0.1,<5.0.0) ; python_version < "3.11"
Project-URL: Homepage, https://rosetta-api.docs.careevolution.com/
